cool_util/__init__.py
cool_util-0.0.1.dist-info/WHEEL
cool_util-0.0.1.dist-info/METADATA
cool_util-0.0.1.dist-info/RECORD
