Metadata-Version: 2.1
Name: cool_util
Version: 0.0.1
Summary: common util
Author: eabiao
Author-email: eabiao@163.com
Classifier: License :: OSI Approved :: MIT License
Classifier: Operating System :: OS Independent
Classifier: Programming Language :: Python :: 3
